pylearner/__init__.py
pylearner/exception.py
pylearner/help.py
pylearner/introduction.py
pylearner/loader.py
pylearner/test.py
pylearner-0.0.3.data/data/lib/site-packages/pylearner/packages/test.pylearner
pylearner-0.0.3.dist-info/LICENSE
pylearner-0.0.3.dist-info/METADATA
pylearner-0.0.3.dist-info/WHEEL
pylearner-0.0.3.dist-info/top_level.txt
pylearner-0.0.3.dist-info/RECORD
